autoplotlib/__init__.py
autoplotlib/main.py
autoplotlib/sandbox.py
autoplotlib-0.1.0.dist-info/METADATA
autoplotlib-0.1.0.dist-info/WHEEL
autoplotlib-0.1.0.dist-info/licenses/LICENSE
autoplotlib-0.1.0.dist-info/RECORD
