Metadata-Version: 2.1
Name: autoplotlib
Version: 0.1.0
Summary: Single-line plots from language prompt in Python.
Project-URL: Homepage, https://github.com/rdnfn/autoplotlib
Project-URL: Bug Tracker, https://github.com/rdnfn/autoplotlib/issues
Author-email: rdnfn <info@arduin.io>
License-File: LICENSE
Classifier: License :: OSI Approved :: MIT License
Classifier: Operating System :: OS Independent
Classifier: Programming Language :: Python :: 3
Requires-Python: >=3.7
Requires-Dist: langchain
Requires-Dist: matplotlib
Provides-Extra: dev
Requires-Dist: pytest; extra == 'dev'
